tech/__init__.py
tech/mlsql/__init__.py
tech/mlsql/serviceframework/__init__.py
tech/mlsql/serviceframework/sdk/__init__.py
tech/mlsql/serviceframework/sdk/app_runtime.py
tech/mlsql/serviceframework/sdk/version.py
tech/mlsql/serviceframework/sdk/plugins/__init__.py
tech/mlsql/serviceframework/sdk/plugins/ar_python.py
tech/mlsql/serviceframework/sdk/plugins/user_system.py
tech/mlsql/serviceframework/sdk/tests/__init__.py
tech/mlsql/serviceframework/sdk/tests/test.py
web_platform_py_sdk-0.1.0.dist-info/METADATA
web_platform_py_sdk-0.1.0.dist-info/RECORD
web_platform_py_sdk-0.1.0.dist-info/WHEEL
web_platform_py_sdk-0.1.0.dist-info/top_level.txt
